.gitignore
README.rst
bootstrap.py
buildout.cfg
gitexternals.cfg
setup.py
config/gitctl.cfg.sample
config/gitexternals.cfg.sample
gitctl/__init__.py
gitctl/command.py
gitctl/notification.py
gitctl/parser.py
gitctl/tests.py
gitctl/utils.py
gitctl/wtf.py
gitctl.egg-info/PKG-INFO
gitctl.egg-info/SOURCES.txt
gitctl.egg-info/dependency_links.txt
gitctl.egg-info/entry_points.txt
gitctl.egg-info/requires.txt
gitctl.egg-info/top_level.txt
gitctl.egg-info/zip-safe