Metadata-Version: 1.0
Name: gitctl
Version: 2.0a8
Summary: A particular Git workflow implementation with a development/staging/production code-flow model and support for multiple repositories as part of a larger project.
Home-page: http://github.com/dokai/gitctl
Author: Kai Lautaportti
Author-email: kai.lautaportti@hexagonit.fi
License: BSD
Keywords: git workflow
Platform: UNKNOWN
Classifier: Development Status :: 3 - Alpha
Classifier: Environment :: Console
Classifier: Intended Audience :: Developers
Classifier: License :: OSI Approved :: BSD License
Classifier: Programming Language :: Python
Classifier: Topic :: Software Development :: Version Control
Classifier: Topic :: Software Development :: Build Tools
